[
  {
    "model": "users.person",
    "pk": 2,
    "fields": {
      "password": "pbkdf2_sha256$100000$PPfl9Zgp4TAT$IVkgURQwWGd6pnhj4KYrsnf8Zgbu85R4v4vVd9v2qa8=",
      "last_login": "2018-02-12T12:50:31.044Z",
      "is_superuser": true,
      "username": "admin",
      "first_name": "",
      "last_name": "",
      "email": "",
      "is_staff": true,
      "date_joined": "2018-02-12T12:12:44.518Z",
      "is_active": true,
      "groups": [],
      "user_permissions": []
    }
  },
  {
    "model": "users.person",
    "pk": 3,
    "fields": {
      "password": "pbkdf2_sha256$100000$CaaFigSWCCy7$2d4gZ6Ld6a+QskgqHLLhKNl6DfClwDJvdcsFXfaATO4=",
      "last_login": null,
      "is_superuser": false,
      "username": "nikita3",
      "first_name": "",
      "last_name": "",
      "email": "",
      "is_staff": false,
      "date_joined": "2018-02-12T12:19:12.793Z",
      "is_active": true,
      "groups": [],
      "user_permissions": []
    }
  },
  {
    "model": "users.person",
    "pk": 4,
    "fields": {
      "password": "pbkdf2_sha256$100000$PsI5aGu5hSVO$TnAXvJvwPtUN5GNHUblsmmIlfKQFOJCZpfuKFFRvqHI=",
      "last_login": null,
      "is_superuser": false,
      "username": "denis4",
      "first_name": "",
      "last_name": "",
      "email": "",
      "is_staff": false,
      "date_joined": "2018-02-12T12:23:23.121Z",
      "is_active": true,
      "groups": [],
      "user_permissions": []
    }
  },
  {
    "model": "users.person",
    "pk": 5,
    "fields": {
      "password": "pbkdf2_sha256$100000$Ay6sojcimQaF$QfwYn4W5eRodfGlFyXHHKB5TSFcmyWpzmrV5kpM2+us=",
      "last_login": null,
      "is_superuser": false,
      "username": "artem5",
      "first_name": "",
      "last_name": "",
      "email": "",
      "is_staff": false,
      "date_joined": "2018-02-12T12:23:38.151Z",
      "is_active": true,
      "groups": [],
      "user_permissions": []
    }
  },
  {
    "model": "users.friend",
    "pk": 1,
    "fields": {
      "first": 3,
      "second": 4
    }
  },
  {
    "model": "users.friend",
    "pk": 2,
    "fields": {
      "first": 4,
      "second": 3
    }
  },
  {
    "model": "users.friend",
    "pk": 3,
    "fields": {
      "first": 3,
      "second": 5
    }
  },
  {
    "model": "users.friend",
    "pk": 4,
    "fields": {
      "first": 5,
      "second": 3
    }
  },
  {
    "model": "users.friend",
    "pk": 5,
    "fields": {
      "first": 4,
      "second": 5
    }
  },
  {
    "model": "users.friend",
    "pk": 6,
    "fields": {
      "first": 5,
      "second": 4
    }
  }
]